MANIFEST.in
README.rst
setup.py
django_skosxl.egg-info/PKG-INFO
django_skosxl.egg-info/SOURCES.txt
django_skosxl.egg-info/dependency_links.txt
django_skosxl.egg-info/not-zip-safe
django_skosxl.egg-info/top_level.txt
skosxl/__init__.py
skosxl/admin.py
skosxl/models.py
skosxl/urls.py
skosxl/views.py
skosxl/locale/fr/LC_MESSAGES/django.mo
skosxl/locale/fr/LC_MESSAGES/django.po
skosxl/migrations/0001_initial.py
skosxl/migrations/__init__.py
skosxl/static/d3.js
skosxl/static/d3.layout.js
skosxl/static/d3.tree.css
skosxl/static/d3.tree.js
skosxl/templates/admin_concept_change.html
skosxl/templates/admin_concept_list.html
skosxl/templates/concept_detail.html
skosxl/templates/scheme_detail.html
skosxl/templates/tag_detail.html
skosxl/templates/admin/autocomplete/fk_searchinput.html
skosxl/templates/admin/autocomplete/inline_searchinput.html
skosxl/templates/admin/autocomplete/nolookups_foreignkey_searchinput.html
skosxl/utils/__init__.py
skosxl/utils/autocomplete_admin.py
skosxl/utils/cors.py