Metadata-Version: 1.0
Name: django-skosxl
Version: 0.3
Summary: Pluggable django application for managing a SKOS-XL Thesaurus, based on a tag folksonomy
Home-page: UNKNOWN
Author: Dominique Guardiola
Author-email: dguardiola@quinode.fr
License: BSD
Platform: UNKNOWN
